traopy_util-0.1.2.dist-info/METADATA
traopy_util-0.1.2.dist-info/WHEEL
traopy_util/util/common.pyi
traopy_util/util/__init__.pyi
traopy_util/util/v0.pyi
traopy_util/util.cpython-312-x86_64-linux-gnu.so
traopy_util-0.1.2.dist-info/RECORD
