Metadata-Version: 2.4
Name: traopy_util
Version: 0.1.2
Classifier: Programming Language :: Python :: 3.12
Summary: Library module for exec-container environment of traO-Judge
Requires-Python: >=3.8
